libertem/__init__.py
libertem/__version__.py
libertem/_baked_revision.py
libertem/api.py
libertem/cli_tweaks.py
libertem/exceptions.py
libertem/masks.py
libertem/preload.py
libertem/versioning.py
libertem/warnings.py
libertem/analysis/__init__.py
libertem/analysis/apply_fft_mask.py
libertem/analysis/base.py
libertem/analysis/clust.py
libertem/analysis/com.py
libertem/analysis/disk.py
libertem/analysis/fem.py
libertem/analysis/fullmatch.py
libertem/analysis/getroi.py
libertem/analysis/gridmatching.py
libertem/analysis/helper.py
libertem/analysis/masks.py
libertem/analysis/point.py
libertem/analysis/radialfourier.py
libertem/analysis/raw.py
libertem/analysis/rawfft.py
libertem/analysis/ring.py
libertem/analysis/sd.py
libertem/analysis/sum.py
libertem/analysis/sumfft.py
libertem/analysis/sumsig.py
libertem/common/__init__.py
libertem/common/analysis.py
libertem/common/async_utils.py
libertem/common/backend.py
libertem/common/buffers.py
libertem/common/container.py
libertem/common/exceptions.py
libertem/common/executor.py
libertem/common/math.py
libertem/common/messageconverter.py
libertem/common/progress.py
libertem/common/scheduler.py
libertem/common/shape.py
libertem/common/slice.py
libertem/common/snooze.py
libertem/common/sparse.py
libertem/common/subscriptions.py
libertem/common/threading.py
libertem/common/tracing.py
libertem/common/udf.py
libertem/common/viz.py
libertem/common/win_tweaks.py
libertem/common/numba/__init__.py
libertem/common/numba/cache.py
libertem/contrib/__init__.py
libertem/contrib/convert_transposed.py
libertem/contrib/daskadapter.py
libertem/corrections/__init__.py
libertem/corrections/coordinates.py
libertem/corrections/corrset.py
libertem/corrections/detector.py
libertem/executor/__init__.py
libertem/executor/base.py
libertem/executor/cli.py
libertem/executor/concurrent.py
libertem/executor/dask.py
libertem/executor/delayed.py
libertem/executor/inline.py
libertem/executor/integration.py
libertem/executor/pipelined.py
libertem-0.15.2.dist-info/METADATA
libertem-0.15.2.dist-info/WHEEL
libertem-0.15.2.dist-info/entry_points.txt
libertem-0.15.2.dist-info/licenses/LICENSE
libertem-0.15.2.dist-info/RECORD
