Metadata-Version: 2.4
Name: libertem
Version: 0.15.2
Summary: Open pixelated STEM framework
Project-URL: Repository, https://github.com/LiberTEM/LiberTEM
Project-URL: Homepage, https://libertem.github.io/LiberTEM/
Author-email: the LiberTEM team <libertem-dev@googlegroups.com>
License: Copyright (c) 2024 LiberTEM creators
License-File: LICENSE
Keywords: electron,microscopy
Classifier: Development Status :: 5 - Production/Stable
Classifier: Environment :: Console
Classifier: Environment :: Web Environment
Classifier: Intended Audience :: Developers
Classifier: Intended Audience :: End Users/Desktop
Classifier: Intended Audience :: Science/Research
Classifier: License :: OSI Approved :: MIT License
Classifier: Natural Language :: English
Classifier: Operating System :: MacOS :: MacOS X
Classifier: Operating System :: Microsoft :: Windows
Classifier: Operating System :: POSIX :: Linux
Classifier: Programming Language :: JavaScript
Classifier: Programming Language :: Python :: 3.9
Classifier: Programming Language :: Python :: 3.10
Classifier: Programming Language :: Python :: 3.11
Classifier: Programming Language :: Python :: 3.12
Classifier: Programming Language :: Python :: 3.13
Classifier: Topic :: Scientific/Engineering
Classifier: Topic :: Scientific/Engineering :: Physics
Classifier: Topic :: Scientific/Engineering :: Visualization
Requires-Python: >=3.9.3
Requires-Dist: autopep8
Requires-Dist: click
Requires-Dist: cloudpickle
Requires-Dist: colorcet
Requires-Dist: dask!=2023.6.1
Requires-Dist: defusedxml
Requires-Dist: distributed>=2.19.0
Requires-Dist: h5py
Requires-Dist: ipympl
Requires-Dist: jsonschema
Requires-Dist: jupyter-ui-poll
Requires-Dist: matplotlib
Requires-Dist: nbconvert
Requires-Dist: nbformat
Requires-Dist: ncempy>=1.10
Requires-Dist: numba>0.61.2; python_full_version == '3.13.4'
Requires-Dist: numba>=0.53; python_version < '3.10'
Requires-Dist: numba>=0.55; python_version < '3.11' and python_version >= '3.10'
Requires-Dist: numba>=0.57; python_version < '3.12' and python_version >= '3.11'
Requires-Dist: numba>=0.59; python_version < '3.13' and python_version >= '3.12'
Requires-Dist: numba>=0.61; python_version < '3.14' and python_version >= '3.13' and python_full_version != '3.13.4'
Requires-Dist: numba>=0.61; python_version >= '3.14'
Requires-Dist: numexpr!=2.8.6
Requires-Dist: numpy
Requires-Dist: opentelemetry-api
Requires-Dist: pillow
Requires-Dist: psutil
Requires-Dist: pywin32!=226; platform_system == 'Windows'
Requires-Dist: scikit-image
Requires-Dist: scikit-learn
Requires-Dist: scipy>=1.4.1
Requires-Dist: sparse
Requires-Dist: sparseconverter>=0.4.0
Requires-Dist: tblib
Requires-Dist: threadpoolctl>=3.0
Requires-Dist: tomli
Requires-Dist: tornado>=5
Requires-Dist: tqdm
Requires-Dist: typing-extensions
Provides-Extra: bqplot
Requires-Dist: bqplot; extra == 'bqplot'
Requires-Dist: bqplot-image-gl; extra == 'bqplot'
Requires-Dist: ipython; extra == 'bqplot'
Provides-Extra: cupy
Requires-Dist: cupy; extra == 'cupy'
Provides-Extra: hdbscan
Requires-Dist: hdbscan; (python_version != '3.11' or platform_system != 'Windows') and extra == 'hdbscan'
Requires-Dist: hdbscan<=0.8.30; (python_version == '3.11' and platform_system == 'Windows') and extra == 'hdbscan'
Provides-Extra: hdf5plugin
Requires-Dist: hdf5plugin; extra == 'hdf5plugin'
Provides-Extra: torch
Requires-Dist: torch; extra == 'torch'
Provides-Extra: tracing
Requires-Dist: opentelemetry-distro; extra == 'tracing'
Requires-Dist: opentelemetry-exporter-otlp; extra == 'tracing'
